{
  "type": "FeatureCollection",
  "features": [
    {
      "type": "Feature",
      "geometry": {
        "type": "Point",
        "coordinates": [
          -81.76,
          24.5561,
          1
        ]
      },
      "properties": {
        "title": "Key West / Key West_intl",
        "marker-symbol": "airport"
      }
    },
    {
      "type": "Feature",
      "geometry": {
        "type": "Point",
        "coordinates": [
          -81.76764761743071,
          24.55597839079851,
          1
        ]
      },
      "properties": {
        "title": "09",
        "marker-symbol": "triangle"
      }
    },
    {
      "type": "Feature",
      "geometry": {
        "type": "Point",
        "coordinates": [
          -81.75235236775978,
          24.55622122335174,
          1
        ]
      },
      "properties": {
        "title": "27",
        "marker-symbol": "triangle-stroked"
      }
    },
    {
      "type": "Feature",
      "geometry": {
        "type": "Point",
        "coordinates": [
          -81.62733760225574,
          24.670965048150805,
          594.0499343720172
        ]
      },
      "properties": {
        "title": "C172",
        "marker-symbol": "airfield"
      }
    },
    {
      "type": "Feature",
      "geometry": {
        "type": "Point",
        "coordinates": [
          -81.76031962456504,
          24.572752899101005,
          1
        ]
      },
      "properties": {
        "title": "09-ENTRY",
        "marker-symbol": "racetrack"
      }
    }
  ]
}